pyopenspecy/__init__.py
pyopenspecy/__version__.py
pyopenspecy/pyopenspecy.py
pyopenspecy/data/__init__.py
pyopenspecy/data/ftir_library.csv
pyopenspecy/data/ftir_metadata.csv
pyopenspecy/data/raman_library.csv
pyopenspecy/data/raman_metadata.csv
pyopenspecy-0.0.1.dist-info/METADATA
pyopenspecy-0.0.1.dist-info/WHEEL
pyopenspecy-0.0.1.dist-info/top_level.txt
pyopenspecy-0.0.1.dist-info/RECORD
